{
  "recentFiles": [
    {
      "basename": "Anton Abbac",
      "path": "02 - Projects/01 - END plan - Q/Anton Abbac.md"
    },
    {
      "basename": "20251024",
      "path": "06 - Journal/00 - Daily/20251024.md"
    },
    {
      "basename": "20251007",
      "path": "06 - Journal/00 - Daily/20251007.md"
    },
    {
      "basename": "20251006",
      "path": "06 - Journal/00 - Daily/20251006.md"
    },
    {
      "basename": "20251012",
      "path": "06 - Journal/00 - Daily/20251012.md"
    },
    {
      "basename": "20251011",
      "path": "06 - Journal/00 - Daily/20251011.md"
    },
    {
      "basename": "20251008",
      "path": "06 - Journal/00 - Daily/20251008.md"
    },
    {
      "basename": "Index",
      "path": "02 - Projects/01 - END plan - Q/Index.md"
    },
    {
      "basename": "20251003",
      "path": "06 - Journal/00 - Daily/20251003.md"
    },
    {
      "basename": "20251001",
      "path": "06 - Journal/00 - Daily/20251001.md"
    },
    {
      "basename": "20251023",
      "path": "06 - Journal/00 - Daily/20251023.md"
    },
    {
      "basename": "20251015",
      "path": "06 - Journal/00 - Daily/20251015.md"
    },
    {
      "basename": "20251022",
      "path": "06 - Journal/00 - Daily/20251022.md"
    },
    {
      "basename": "README",
      "path": "02 - Projects/01 - END plan - Q/README.md"
    },
    {
      "basename": "(TEMPLATE) System Module",
      "path": "99 - Meta/00 - Templates/(TEMPLATE) System Module.md"
    },
    {
      "basename": "(TEMPLATE) Checklist Module",
      "path": "99 - Meta/00 - Templates/(TEMPLATE) Checklist Module.md"
    },
    {
      "basename": "(TEMPLATE) Planning Module",
      "path": "99 - Meta/00 - Templates/(TEMPLATE) Planning Module.md"
    },
    {
      "basename": "Empty",
      "path": "03 - Areas/05 - Studys/Manipulation Techniques/Empty.md"
    },
    {
      "basename": "Full Body Training",
      "path": "03 - Areas/01 - Habits & Routines/03 - Exercise routine/Full Body Training.md"
    },
    {
      "basename": "Linguagem Comportamental - Q1",
      "path": "08 - Archives/Deprecated Projects/01 - Abbac Plan - Q/00 - Mente/Linguagem Comportamental - Q1.md"
    },
    {
      "basename": "Routine",
      "path": "03 - Areas/01 - Habits & Routines/01 - Daily Routines/Routine.md"
    },
    {
      "basename": "(TEMPLATE) Daily Definitive – Prime",
      "path": "99 - Meta/00 - Templates/(TEMPLATE) Daily Definitive – Prime.md"
    },
    {
      "basename": "MOC - Abbac Plan - Q",
      "path": "08 - Archives/Deprecated Moc's/MOC - Abbac Plan - Q.md"
    },
    {
      "basename": "(TEMPLATE) Permanent R",
      "path": "08 - Archives/Old Templates/(TEMPLATE) Permanent R.md"
    },
    {
      "basename": "(TEMPLATE) Permanent",
      "path": "08 - Archives/Old Templates/(TEMPLATE) Permanent.md"
    },
    {
      "basename": "(TEMPLATE) Literature PS",
      "path": "08 - Archives/Old Templates/(TEMPLATE) Literature PS.md"
    },
    {
      "basename": "(TEMPLATE) Literature",
      "path": "08 - Archives/Old Templates/(TEMPLATE) Literature.md"
    },
    {
      "basename": "(TEMPLATE) Daily Definitive",
      "path": "08 - Archives/Old Templates/(TEMPLATE) Daily Definitive.md"
    },
    {
      "basename": "202510111516 A Estrutura de Pastas que Todo Dev Front-End Deveria Conhecer",
      "path": "04 - Resources/Articles/202510111516 A Estrutura de Pastas que Todo Dev Front-End Deveria Conhecer.md"
    },
    {
      "basename": "202510121654 Periodic CSS",
      "path": "00 - Inbox/202510121654 Periodic CSS.md"
    },
    {
      "basename": "202509281931 Lista de minhas prendas para gincana",
      "path": "00 - Inbox/202509281931 Lista de minhas prendas para gincana.md"
    },
    {
      "basename": "202510181142 Comparação objetiva com outros sites",
      "path": "00 - Inbox/202510181142 Comparação objetiva com outros sites.md"
    },
    {
      "basename": "202510212042 Treino de Muay Thai",
      "path": "05 - Zettelkasten PS/00 - Fleeting IP/202510212042 Treino de Muay Thai.md"
    },
    {
      "basename": "20250901",
      "path": "06 - Journal/00 - Daily/20250901.md"
    },
    {
      "basename": "Daily Routine 2.0",
      "path": "08 - Archives/Deprecated Notes/Daily Routine 2.0.md"
    },
    {
      "basename": "202510111551 Código fornecido pelo professor",
      "path": "02 - Projects/03 - Khronus/202510111551 Código fornecido pelo professor.md"
    },
    {
      "basename": "202509110859 Tabalho de Lógica Computacional",
      "path": "02 - Projects/03 - Khronus/202509110859 Tabalho de Lógica Computacional.md"
    },
    {
      "basename": "202510152121 Lore dos cavaleiros de Deus",
      "path": "03 - Areas/06 - Roleplay/Main Story/202510152121 Lore dos cavaleiros de Deus.md"
    },
    {
      "basename": "202507242239 Poesia para Maria Eduarda",
      "path": "03 - Areas/03- Relationships/Maria Eduarda Lau - First GF/202507242239 Poesia para Maria Eduarda.md"
    },
    {
      "basename": "202507261959 Texto de intenções de relacionamento para Maria Eduarda",
      "path": "03 - Areas/03- Relationships/Maria Eduarda Lau - First GF/202507261959 Texto de intenções de relacionamento para Maria Eduarda.md"
    },
    {
      "basename": "202508102233 Filmes recomendados pela Maria Eduarda Lau",
      "path": "03 - Areas/03- Relationships/Maria Eduarda Lau - First GF/202508102233 Filmes recomendados pela Maria Eduarda Lau.md"
    },
    {
      "basename": "202508102233 Preferência de anel",
      "path": "03 - Areas/03- Relationships/Maria Eduarda Lau - First GF/202508102233 Preferência de anel.md"
    },
    {
      "basename": "202508112055 Texto sobre Anton e Maria Eduarda",
      "path": "03 - Areas/03- Relationships/Maria Eduarda Lau - First GF/202508112055 Texto sobre Anton e Maria Eduarda.md"
    },
    {
      "basename": "202508112057 O dia após o quase término",
      "path": "03 - Areas/03- Relationships/Maria Eduarda Lau - First GF/202508112057 O dia após o quase término.md"
    },
    {
      "basename": "202508192222 nome irmã da minha gf",
      "path": "03 - Areas/03- Relationships/Maria Eduarda Lau - First GF/202508192222 nome irmã da minha gf.md"
    },
    {
      "basename": "202509241456 Revelação do TPA",
      "path": "03 - Areas/03- Relationships/Maria Eduarda Lau - First GF/202509241456 Revelação do TPA.md"
    },
    {
      "basename": "202509111941 Plano para sair no cinema",
      "path": "03 - Areas/03- Relationships/Maria Eduarda Lau - First GF/202509111941 Plano para sair no cinema.md"
    },
    {
      "basename": "202508271255 Oque a Maria acha de relação a base de trocas",
      "path": "03 - Areas/03- Relationships/Maria Eduarda Lau - First GF/202508271255 Oque a Maria acha de relação a base de trocas.md"
    },
    {
      "basename": "2025",
      "path": "06 - Journal/03 - Annual Mission/2025.md"
    },
    {
      "basename": "Daily Training",
      "path": "03 - Areas/01 - Habits & Routines/03 - Exercise routine/Daily Training.md"
    }
  ],
  "omittedPaths": [],
  "omittedTags": [],
  "updateOn": "file-open",
  "omitBookmarks": false
}